odoo8_addon_hr_employee_firstname-8.0.0.0.2.99.dev10-py2.7-nspkg.pth
odoo8_addon_hr_employee_firstname-8.0.0.0.2.99.dev10.dist-info/DESCRIPTION.rst
odoo8_addon_hr_employee_firstname-8.0.0.0.2.99.dev10.dist-info/METADATA
odoo8_addon_hr_employee_firstname-8.0.0.0.2.99.dev10.dist-info/RECORD
odoo8_addon_hr_employee_firstname-8.0.0.0.2.99.dev10.dist-info/WHEEL
odoo8_addon_hr_employee_firstname-8.0.0.0.2.99.dev10.dist-info/metadata.json
odoo8_addon_hr_employee_firstname-8.0.0.0.2.99.dev10.dist-info/namespace_packages.txt
odoo8_addon_hr_employee_firstname-8.0.0.0.2.99.dev10.dist-info/top_level.txt
odoo_addons/hr_employee_firstname/README.rst
odoo_addons/hr_employee_firstname/__init__.py
odoo_addons/hr_employee_firstname/__openerp__.py
odoo_addons/hr_employee_firstname/i18n/ar.po
odoo_addons/hr_employee_firstname/i18n/de.po
odoo_addons/hr_employee_firstname/i18n/es.po
odoo_addons/hr_employee_firstname/i18n/fi.po
odoo_addons/hr_employee_firstname/i18n/fr.po
odoo_addons/hr_employee_firstname/i18n/hr_employee_firstname.pot
odoo_addons/hr_employee_firstname/i18n/it.po
odoo_addons/hr_employee_firstname/i18n/nl.po
odoo_addons/hr_employee_firstname/i18n/nl_NL.po
odoo_addons/hr_employee_firstname/i18n/pt_BR.po
odoo_addons/hr_employee_firstname/i18n/ro.po
odoo_addons/hr_employee_firstname/i18n/sl.po
odoo_addons/hr_employee_firstname/models/__init__.py
odoo_addons/hr_employee_firstname/models/hr_employee.py
odoo_addons/hr_employee_firstname/static/description/icon.png
odoo_addons/hr_employee_firstname/tests/__init__.py
odoo_addons/hr_employee_firstname/tests/test_hr_employee_firstname.py
odoo_addons/hr_employee_firstname/views/hr_view.xml
