Metadata-Version: 2.0
Name: odoo8-addon-hr-employee-firstname
Version: 8.0.0.0.2.99.dev10
Summary: Adds First Name to Employee
Home-page: http://www.savoirfairelinux.com
Author: Savoir-faire Linux, Fekete Mihai (Forest and Biomass Services Romania), Odoo Community Association (OCA)
Author-email: support@odoo-community.org
License: AGPL-3
Platform: UNKNOWN
Classifier: Programming Language :: Python
Classifier: Framework :: Odoo
Classifier: License :: OSI Approved :: GNU Affero General Public License v3
Requires-Python: ~=2.7
Requires-Dist: odoo (<9.0a,>=8.0a)
Requires-Dist: odoo8-addon-partner-firstname
